pylick/__config__.py
pylick/__init__.py
pylick/__version__.py
pylick/analysis.py
pylick/data/index_table.dat
pylick/data/plotbelli.style
pylick/indices.py
pylick/io.py
pylick/measurement.py
pylick/plot.py
pylick-1.0.2.dist-info/LICENSE
pylick-1.0.2.dist-info/METADATA
pylick-1.0.2.dist-info/WHEEL
pylick-1.0.2.dist-info/RECORD
