Metadata-Version: 2.1
Name: pylick
Version: 1.0.2
Summary: Python tool to measure spectral features in galaxy spectra
Home-page: https://gitlab.com/mmoresco/pylick/
License: GPLv3
Author: Michele Moresco
Author-email: michele.moresco@unibo.it
Requires-Python: >=3.8
Classifier: License :: Other/Proprietary License
Classifier: Programming Language :: Python :: 3
Classifier: Programming Language :: Python :: 3.8
Classifier: Programming Language :: Python :: 3.9
Classifier: Programming Language :: Python :: 3.10
Classifier: Programming Language :: Python :: 3.11
Provides-Extra: docs
Requires-Dist: astropy (>=5.2,<6.0)
Requires-Dist: docutils (>=0.17.1,<0.18.0) ; extra == "docs"
Requires-Dist: myst-parser (>=0.18.1,<0.19.0) ; extra == "docs"
Requires-Dist: nbsphinx (>=0.8.10) ; extra == "docs"
Requires-Dist: numpy (>=1.16)
Requires-Dist: readthedocs-sphinx-search (>=0.1.2,<0.2.0) ; extra == "docs"
Requires-Dist: requests (>=2.31.0,<3.0.0)
Requires-Dist: scipy (>=1.7)
Requires-Dist: sphinx (==5.3.0) ; extra == "docs"
Requires-Dist: sphinx-book-theme (>=1.0) ; extra == "docs"
Requires-Dist: sphinx-copybutton (>=0.5.1,<0.6.0) ; extra == "docs"
Project-URL: Documentation, https://pylick.readthedocs.io/
Project-URL: Repository, https://gitlab.com/mmoresco/pylick/
